aissemble_core_bom/__init__.py
aissemble_core_bom/training_bom.py
aissemble_core_config/__init__.py
aissemble_core_config/messaging_config.py
aissemble_core_config/spark_elasticsearch_config.py
aissemble_core_config/spark_neo4j_config.py
aissemble_core_config/spark_postgres_config.py
aissemble_core_config/spark_rdbms_config.py
aissemble_core_filestore/__init__.py
aissemble_core_filestore/file_store_factory.py
aissemble_core_metadata/__init__.py
aissemble_core_metadata/hive_metadata_api_service.py
aissemble_core_metadata/logging_metadata_api_service.py
aissemble_core_metadata/metadata_api.py
aissemble_core_metadata/metadata_model.py
aissembleauth/__init__.py
aissembleauth/auth_config.py
aissembleauth/json_web_token_util.py
inference/__init__.py
inference/inference_client.py
inference/inference_config.py
inference/inference_request.py
inference/inference_request_batch.py
inference/inference_result.py
inference/inference_result_batch.py
inference/rest_inference_client.py
policy_manager/__init__.py
policy_manager/abstract_policy_manager.py
policy_manager/configuration/__init__.py
policy_manager/configuration/policy_configuration.py
policy_manager/default_policy_manager.py
policy_manager/policy/__init__.py
policy_manager/policy/json/__init__.py
policy_manager/policy/json/policy_input.py
policy_manager/policy/policy.py
policy_manager/policy/result/__init__.py
policy_manager/policy/result/policy_invocation_result.py
aissemble_foundation_core_python-2.0.0.dist-info/LICENSE
aissemble_foundation_core_python-2.0.0.dist-info/METADATA
aissemble_foundation_core_python-2.0.0.dist-info/WHEEL
aissemble_foundation_core_python-2.0.0.dist-info/RECORD
