Metadata-Version: 2.3
Name: aissemble-foundation-core-python
Version: 2.0.0
Summary: Core classes for supporting concepts (alerting, metadata, etc) that are needed across most Python-based components
License: Apache-2.0
Author: aiSSEMBLE Baseline Community
Author-email: aissemble@bah.com
Requires-Python: >=3.9
Classifier: License :: OSI Approved :: Apache Software License
Classifier: Programming Language :: Python :: 3
Classifier: Programming Language :: Python :: 3.9
Classifier: Programming Language :: Python :: 3.10
Classifier: Programming Language :: Python :: 3.11
Classifier: Programming Language :: Python :: 3.12
Classifier: Programming Language :: Python :: 3.13
Requires-Dist: aiohttp (>=3.8.0)
Requires-Dist: apache-libcloud (>=3.6.0)
Requires-Dist: cryptography (>=42.0.4)
Requires-Dist: jsonpickle (>=2.1.0)
Requires-Dist: kafka-python (>=2.0.2,<3.0.0)
Requires-Dist: krausening (>=21)
Requires-Dist: psycopg2-binary (>=2.9.6,<3.0.0)
Requires-Dist: pydantic (>=2.8.0)
Requires-Dist: pyjks (>=20.0.0)
Requires-Dist: pyjwt (>=2.3.0)
Requires-Dist: sqlalchemy (>=2.0.16,<3.0.0)
Requires-Dist: urllib3 (>=2.5.0,<3.0.0)
Project-URL: Documentation, https://boozallen.github.io/aissemble
Project-URL: Homepage, https://github.com/boozallen/aissemble
Project-URL: Repository, https://github.com/boozallen/aissemble
